torcello.py
Torcello-0.3.1.dist-info/METADATA
Torcello-0.3.1.dist-info/WHEEL
Torcello-0.3.1.dist-info/top_level.txt
Torcello-0.3.1.dist-info/RECORD
