Metadata-Version: 2.1
Name: Torcello
Version: 0.3.1
Summary: Just a Python module suitable to use multiple Tor circuits at the same time
Home-page: https://github.com/barjomet/torcello
Author: Oleksii Ivanchuk
Author-email: barjomet@barjomet.com
License: BSD
Keywords: tor,socks,proxy
Platform: UNKNOWN
Classifier: Development Status :: 4 - Beta
Classifier: Intended Audience :: Developers
Classifier: Operating System :: MacOS :: MacOS X
Classifier: Operating System :: Microsoft :: Windows
Classifier: Operating System :: POSIX
Classifier: Programming Language :: Python
Requires-Dist: pysocks
